README.md
setup.cfg
setup.py
pyfpds/__init__.py
pyfpds/pyfpds.py
pyfpds.egg-info/PKG-INFO
pyfpds.egg-info/SOURCES.txt
pyfpds.egg-info/dependency_links.txt
pyfpds.egg-info/not-zip-safe
pyfpds.egg-info/requires.txt
pyfpds.egg-info/top_level.txt