Metadata-Version: 1.1
Name: pyfpds
Version: 0.2.0
Summary: pyfpds is a python wrapper for accessing federal contracting data in the Federal Procurement Data System (FPDS)
Home-page: https://github.com/propublica/pyfpds
Author: Kaitlin Devine, Derek Willis
Author-email: derek.willis@propublica.org
License: BSD
Keywords: pyfpds
Platform: UNKNOWN
Classifier: Development Status :: 2 - Pre-Alpha
Classifier: Intended Audience :: Developers
Classifier: License :: OSI Approved :: BSD License
Classifier: Natural Language :: English
Classifier: Programming Language :: Python :: 2
Classifier: Programming Language :: Python :: 2.6
Classifier: Programming Language :: Python :: 2.7
Classifier: Programming Language :: Python :: 3
Classifier: Programming Language :: Python :: 3.3
Classifier: Programming Language :: Python :: 3.4
